arver/__init__.py
arver/arver_bin_parser.py
arver/arver_discinfo.py
arver/arver_main.py
arver/arver_ripinfo.py
arver/version.py
arver/audio/__init__.py
arver/audio/_audio.abi3.so
arver/audio/_audio.c
arver/audio/checksums.py
arver/audio/properties.py
arver/disc/__init__.py
arver/disc/database.py
arver/disc/fingerprint.py
arver/disc/info.py
arver/disc/utils.py
arver/rip/__init__.py
arver/rip/rip.py
arver.libs/libFLAC-f3ea5d46.so.12.1.0
arver.libs/libogg-d73e40ab.so.0.8.5
arver.libs/libopus-3a3cd1b6.so.0.9.0
arver.libs/libsndfile-4e134b5d.so.1.0.37
arver.libs/libvorbis-002a0750.so.0.4.9
arver.libs/libvorbisenc-045450b3.so.2.0.12
arver-1.5.0.dist-info/LICENSE
arver-1.5.0.dist-info/METADATA
arver-1.5.0.dist-info/WHEEL
arver-1.5.0.dist-info/entry_points.txt
arver-1.5.0.dist-info/top_level.txt
arver-1.5.0.dist-info/RECORD
