Metadata-Version: 2.1
Name: ARver
Version: 1.5.0
Summary: Application for verifying ripped audio files using AccurateRip database.
Author-email: arcctgx <arcctgx@o2.pl>
License: GPLv3
Project-URL: Homepage, https://github.com/arcctgx/ARver
Project-URL: Issues, https://github.com/arcctgx/ARver/issues
Classifier: Development Status :: 5 - Production/Stable
Classifier: Environment :: Console
Classifier: Intended Audience :: End Users/Desktop
Classifier: License :: OSI Approved :: GNU General Public License v3 (GPLv3)
Classifier: Natural Language :: English
Classifier: Operating System :: POSIX :: Linux
Classifier: Programming Language :: C
Classifier: Programming Language :: Python :: 3 :: Only
Classifier: Programming Language :: Python :: 3.7
Classifier: Programming Language :: Python :: 3.8
Classifier: Programming Language :: Python :: 3.9
Classifier: Programming Language :: Python :: 3.10
Classifier: Programming Language :: Python :: 3.11
Classifier: Programming Language :: Python :: 3.12
Classifier: Topic :: Multimedia :: Sound/Audio :: Analysis
Classifier: Topic :: Multimedia :: Sound/Audio :: CD Audio :: CD Ripping
Requires-Python: >=3.7
License-File: LICENSE
Requires-Dist: discid
Requires-Dist: musicbrainzngs
Requires-Dist: pycdio
Requires-Dist: requests
